jackal_protobuf/__init__.py
jackal_protobuf/canine_chain/__init__.py
jackal_protobuf/canine_chain/filetree/__init__.py
jackal_protobuf/canine_chain/filetree/files.proto
jackal_protobuf/canine_chain/filetree/files_pb2.py
jackal_protobuf/canine_chain/filetree/files_pb2_grpc.py
jackal_protobuf/canine_chain/filetree/genesis.proto
jackal_protobuf/canine_chain/filetree/genesis_pb2.py
jackal_protobuf/canine_chain/filetree/genesis_pb2_grpc.py
jackal_protobuf/canine_chain/filetree/params.proto
jackal_protobuf/canine_chain/filetree/params_pb2.py
jackal_protobuf/canine_chain/filetree/params_pb2_grpc.py
jackal_protobuf/canine_chain/filetree/pubkey.proto
jackal_protobuf/canine_chain/filetree/pubkey_pb2.py
jackal_protobuf/canine_chain/filetree/pubkey_pb2_grpc.py
jackal_protobuf/canine_chain/filetree/query.proto
jackal_protobuf/canine_chain/filetree/query_pb2.py
jackal_protobuf/canine_chain/filetree/query_pb2_grpc.py
jackal_protobuf/canine_chain/filetree/tx.proto
jackal_protobuf/canine_chain/filetree/tx_pb2.py
jackal_protobuf/canine_chain/filetree/tx_pb2_grpc.py
jackal_protobuf/canine_chain/jklmint/genesis.proto
jackal_protobuf/canine_chain/jklmint/genesis_pb2.py
jackal_protobuf/canine_chain/jklmint/genesis_pb2_grpc.py
jackal_protobuf/canine_chain/jklmint/minted_block.proto
jackal_protobuf/canine_chain/jklmint/minted_block_pb2.py
jackal_protobuf/canine_chain/jklmint/minted_block_pb2_grpc.py
jackal_protobuf/canine_chain/jklmint/params.proto
jackal_protobuf/canine_chain/jklmint/params_pb2.py
jackal_protobuf/canine_chain/jklmint/params_pb2_grpc.py
jackal_protobuf/canine_chain/jklmint/query.proto
jackal_protobuf/canine_chain/jklmint/query_pb2.py
jackal_protobuf/canine_chain/jklmint/query_pb2_grpc.py
jackal_protobuf/canine_chain/jklmint/tx.proto
jackal_protobuf/canine_chain/jklmint/tx_pb2.py
jackal_protobuf/canine_chain/jklmint/tx_pb2_grpc.py
jackal_protobuf/canine_chain/notifications/genesis.proto
jackal_protobuf/canine_chain/notifications/genesis_pb2.py
jackal_protobuf-0.0.1.dist-info/METADATA
jackal_protobuf-0.0.1.dist-info/WHEEL
jackal_protobuf-0.0.1.dist-info/licenses/LICENSE
jackal_protobuf-0.0.1.dist-info/RECORD
